mem_worker/__init__.py
mem_worker/consumer.py
mem_worker/context.py
mem_worker/executor.py
mem_worker/runtime.py
mem_worker-0.1.10.dist-info/WHEEL
mem_worker-0.1.10.dist-info/entry_points.txt
mem_worker-0.1.10.dist-info/METADATA
mem_worker-0.1.10.dist-info/RECORD
