Metadata-Version: 2.3
Name: mem-worker
Version: 0.1.10
Summary: Worker runtime for memrun services
Author: Julian Mulla
Author-email: Julian Mulla <jmulla@gmail.com>
Requires-Dist: mem-common
Requires-Dist: mem-storage
Requires-Dist: aiokafka>=0.11
Requires-Python: >=3.11
